remote_run_everything/__init__.py
remote_run_everything/binocular/ba_front.py
remote_run_everything/binocular/back_tool.py
remote_run_everything/binocular/cam_tool.py
remote_run_everything/binocular/front_tool.py
remote_run_everything/binocular/relative_pos.py
remote_run_everything/db/__init__.py
remote_run_everything/db/backup.py
remote_run_everything/db/crud_sqlalchemy.py
remote_run_everything/db/crude_duck.py
remote_run_everything/db/kv_store.py
remote_run_everything/deploy/__init__.py
remote_run_everything/deploy/by_http.py
remote_run_everything/deploy/by_http_tool.py
remote_run_everything/deploy/by_sftp.py
remote_run_everything/deploy/process_manage.py
remote_run_everything/deploy/record_mod.py
remote_run_everything/nosql/__init__.py
remote_run_everything/nosql/no_sql.py
remote_run_everything/nosql/no_sql_mysql.py
remote_run_everything/nosql/no_sql_pg.py
remote_run_everything/nosql/no_sql_tool.py
remote_run_everything/tools/__init__.py
remote_run_everything/tools/common.py
remote_run_everything/tools/common1.py
remote_run_everything/tools/decorators.py
remote_run_everything/tools/sqlacodegen_go_struct.py
remote_run_everything/vsconf/conf_txt.py
remote_run_everything/vsconf/core.py
remote_run_everything-2.0.9.dist-info/licenses/LICENSE
remote_run_everything-2.0.9.dist-info/METADATA
remote_run_everything-2.0.9.dist-info/WHEEL
remote_run_everything-2.0.9.dist-info/top_level.txt
remote_run_everything-2.0.9.dist-info/RECORD
