Metadata-Version: 2.4
Name: remote_run_everything
Version: 2.0.9
Summary: Deploy Tools
Author-email: Wang Qi <wangmarkqi@gmail.com>
License-Expression: MIT
Project-URL: Homepage, https://github.com/wangmarkqi/remote_run_everything
Project-URL: Issues, https://github.com/wangmarkqi/remote_run_everything/issues
Classifier: Programming Language :: Python :: 3
Classifier: Operating System :: OS Independent
Requires-Python: >=3.9
License-File: LICENSE
Dynamic: license-file
